{
  "project_info": {
    "project_number": "426657748147",
    "firebase_url": "https://splendid-sonar-238701.firebaseio.com",
    "project_id": "splendid-sonar-238701",
    "storage_bucket": "splendid-sonar-238701.appspot.com"
  },
  "client": [
    {
      "client_info": {
        "mobilesdk_app_id": "1:426657748147:android:48fbf55c3116f1cb",
        "android_client_info": {
          "package_name": "com.example.alcchalenge2"
        }
      },
      "oauth_client": [
        {
          "client_id": "426657748147-lprf0cii8iog0lcve5beljvne5gag259.apps.googleusercontent.com",
          "client_type": 3
        }
      ],
      "api_key": [
        {
          "current_key": "AIzaSyAkmyneCa32m6ZqUR16AcaK3f0U1hMzeeY"
        }
      ],
      "services": {
        "appinvite_service": {
          "other_platform_oauth_client": [
            {
              "client_id": "426657748147-lprf0cii8iog0lcve5beljvne5gag259.apps.googleusercontent.com",
              "client_type": 3
            }
          ]
        }
      }
    },
    {
      "client_info": {
        "mobilesdk_app_id": "1:426657748147:android:eebddd414f1c9fdf",
        "android_client_info": {
          "package_name": "com.example.alcchallenge2"
        }
      },
      "oauth_client": [
        {
          "client_id": "426657748147-1osfpo0rheidkmuq93l83m1ogkev61ic.apps.googleusercontent.com",
          "client_type": 1,
          "android_info": {
            "package_name": "com.example.alcchallenge2",
            "certificate_hash": "20dcee4f88c0af5d8dd5b670b7d5394264f4a3b1"
          }
        },
        {
          "client_id": "426657748147-lprf0cii8iog0lcve5beljvne5gag259.apps.googleusercontent.com",
          "client_type": 3
        }
      ],
      "api_key": [
        {
          "current_key": "AIzaSyAkmyneCa32m6ZqUR16AcaK3f0U1hMzeeY"
        }
      ],
      "services": {
        "appinvite_service": {
          "other_platform_oauth_client": [
            {
              "client_id": "426657748147-lprf0cii8iog0lcve5beljvne5gag259.apps.googleusercontent.com",
              "client_type": 3
            }
          ]
        }
      }
    }
  ],
  "configuration_version": "1"
}